{"PRIMARY:ICARIAN IMAGERY:WATER": 15, "PRIMARY:ICARIAN IMAGERY:DEPTH": 17, "PRIMARY:ICARIAN IMAGERY:DESCENT": 16, "SECONDARY:MORAL IMPERATIVE": 1, "SECONDARY:SOCIAL BEHAVIOR": 36, "PRIMARY:DEFENSIVE SYMBOLIZATION:DIFFUSION": 8, "PRIMARY:REGRESSIVE COGNITION:CONCRETENESS": 98, "PRIMARY:REGRESSIVE COGNITION:BRINK-PASSAGE": 33, "PRIMARY:SENSATION:GENERAL-SENSATION": 1, "SECONDARY:RESTRAINT": 13, "PRIMARY:REGRESSIVE COGNITION:UNKNOWN": 2, "EMOTIONS:EXPRESSIVE BEHAVIOR": 15, "EMOTIONS:GLORY": 9, "PRIMARY:DEFENSIVE SYMBOLIZATION:RANDOM MOVEMENT": 11, "EMOTIONS:ANXIETY": 15, "EMOTIONS:SADNESS": 6, "SECONDARY:TEMPORAL REFERENCES": 86, "PRIMARY:NEED:SEX": 3, "SECONDARY:ORDER": 3, "PRIMARY:SENSATION:SOUND": 19, "PRIMARY:SENSATION:ODOR": 5, "PRIMARY:REGRESSIVE COGNITION:TIMELESSNESS": 2, "PRIMARY:SENSATION:TASTE": 3, "PRIMARY:SENSATION:COLD": 5, "PRIMARY:NEED:ANALITY": 7, "EMOTIONS:AFFECTION": 25, "PRIMARY:NEED:ORALITY": 49, "PRIMARY:DEFENSIVE SYMBOLIZATION:VOYAGE": 4, "EMOTIONS:POSITIVE AFFECT": 10, "PRIMARY:REGRESSIVE COGNITION:NARCISSISM": 68, "PRIMARY:ICARIAN IMAGERY:HEIGHT": 14, "PRIMARY:SENSATION:HARD": 10, "PRIMARY:DEFENSIVE SYMBOLIZATION:PASSIVITY": 28, "EMOTIONS:AGGRESSION": 19, "PRIMARY:SENSATION:SOFT": 6, "PRIMARY:SENSATION:VISION": 36, "PRIMARY:SENSATION:TOUCH": 4, "PRIMARY:REGRESSIVE COGNITION:CONSCIOUSNESS ALTERATION": 9, "PRIMARY:DEFENSIVE SYMBOLIZATION:CHAOS": 3, "SECONDARY:INSTRUMENTAL BEHAVIOR": 33, "PRIMARY:ICARIAN IMAGERY:ASCENT": 5, "PRIMARY:ICARIAN IMAGERY:FIRE": 19, "SECONDARY:ABSTRACTION": 40}