{"PRIMARY:SENSATION:TASTE": 5, "PRIMARY:ICARIAN IMAGERY:DEPTH": 19, "PRIMARY:NEED:ANALITY": 4, "SECONDARY:MORAL IMPERATIVE": 1, "SECONDARY:SOCIAL BEHAVIOR": 32, "PRIMARY:DEFENSIVE SYMBOLIZATION:DIFFUSION": 7, "PRIMARY:REGRESSIVE COGNITION:CONCRETENESS": 75, "PRIMARY:ICARIAN IMAGERY:WATER": 27, "PRIMARY:SENSATION:GENERAL-SENSATION": 2, "SECONDARY:RESTRAINT": 7, "PRIMARY:REGRESSIVE COGNITION:UNKNOWN": 3, "EMOTIONS:EXPRESSIVE BEHAVIOR": 16, "EMOTIONS:GLORY": 5, "PRIMARY:DEFENSIVE SYMBOLIZATION:RANDOM MOVEMENT": 13, "EMOTIONS:ANXIETY": 4, "EMOTIONS:SADNESS": 4, "SECONDARY:TEMPORAL REFERENCES": 28, "PRIMARY:NEED:SEX": 3, "SECONDARY:ORDER": 5, "PRIMARY:SENSATION:SOUND": 29, "PRIMARY:REGRESSIVE COGNITION:TIMELESSNESS": 3, "PRIMARY:SENSATION:COLD": 6, "PRIMARY:ICARIAN IMAGERY:DESCENT": 16, "PRIMARY:SENSATION:VISION": 42, "PRIMARY:NEED:ORALITY": 42, "EMOTIONS:AFFECTION": 9, "PRIMARY:DEFENSIVE SYMBOLIZATION:VOYAGE": 4, "EMOTIONS:POSITIVE AFFECT": 7, "PRIMARY:REGRESSIVE COGNITION:NARCISSISM": 57, "PRIMARY:ICARIAN IMAGERY:HEIGHT": 18, "PRIMARY:SENSATION:HARD": 19, "PRIMARY:DEFENSIVE SYMBOLIZATION:PASSIVITY": 16, "EMOTIONS:AGGRESSION": 22, "PRIMARY:SENSATION:SOFT": 6, "PRIMARY:SENSATION:ODOR": 4, "PRIMARY:SENSATION:TOUCH": 6, "PRIMARY:REGRESSIVE COGNITION:CONSCIOUSNESS ALTERATION": 8, "PRIMARY:DEFENSIVE SYMBOLIZATION:CHAOS": 4, "SECONDARY:INSTRUMENTAL BEHAVIOR": 27, "PRIMARY:ICARIAN IMAGERY:ASCENT": 13, "PRIMARY:ICARIAN IMAGERY:FIRE": 10, "SECONDARY:ABSTRACTION": 20, "PRIMARY:REGRESSIVE COGNITION:BRINK-PASSAGE": 10}